pyhgl/__init__.py
pyhgl/hook.py
pyhgl-0.2.0.dist-info/LICENSE
pyhgl-0.2.0.dist-info/METADATA
pyhgl-0.2.0.dist-info/WHEEL
pyhgl-0.2.0.dist-info/top_level.txt
pyhgl-0.2.0.dist-info/RECORD
