Metadata-Version: 2.1
Name: pyhgl
Version: 0.2.0
Summary: a Python-based Hardware Generation Language
Author-email: Jintao Sun <jintaos2@outlook.com>
Classifier: Programming Language :: Python :: 3
Classifier: License :: OSI Approved :: GNU General Public License (GPL)
Classifier: Operating System :: OS Independent
Requires-Python: >=3.8
License-File: LICENSE
Requires-Dist: gmpy2
Requires-Dist: graphviz
Requires-Dist: numpy
Requires-Dist: pegen
Requires-Dist: pyvcd
